trapi_predict_kit/__init__.py
trapi_predict_kit/config.py
trapi_predict_kit/decorators.py
trapi_predict_kit/py.typed
trapi_predict_kit/save.py
trapi_predict_kit/trapi.py
trapi_predict_kit/trapi_parser.py
trapi_predict_kit/types.py
trapi_predict_kit/utils.py
trapi_predict_kit-0.2.3.dist-info/METADATA
trapi_predict_kit-0.2.3.dist-info/WHEEL
trapi_predict_kit-0.2.3.dist-info/licenses/LICENSE.txt
trapi_predict_kit-0.2.3.dist-info/RECORD
