Metadata-Version: 2.1
Name: trapi-predict-kit
Version: 0.2.3
Summary: A package to help create and deploy Translator Reasoner APIs (TRAPI) from any prediction model exposed as a regular python function.
Project-URL: Homepage, https://github.com/MaastrichtU-IDS/trapi-predict-kit
Project-URL: Documentation, https://github.com/MaastrichtU-IDS/trapi-predict-kit
Project-URL: History, https://github.com/MaastrichtU-IDS/trapi-predict-kit/releases
Project-URL: Tracker, https://github.com/MaastrichtU-IDS/trapi-predict-kit/issues
Project-URL: Source, https://github.com/MaastrichtU-IDS/trapi-predict-kit
Author-email: Vincent Emonet <vincent.emonet@gmail.com>
Maintainer-email: Vincent Emonet <vincent.emonet@gmail.com>
License: MIT License
License-File: LICENSE.txt
Keywords: Python
Classifier: License :: OSI Approved :: MIT License
Classifier: Operating System :: OS Independent
Classifier: Programming Language :: Python :: 3
Classifier: Programming Language :: Python :: 3.7
Classifier: Programming Language :: Python :: 3.8
Classifier: Programming Language :: Python :: 3.9
Classifier: Programming Language :: Python :: 3.10
Classifier: Programming Language :: Python :: 3.11
Requires-Python: >=3.7
Requires-Dist: bmt
Requires-Dist: dvc
Requires-Dist: fastapi>=0.68.1
Requires-Dist: mlem
Requires-Dist: pydantic>=1.9
Requires-Dist: rdflib>=6.1.1
Requires-Dist: reasoner-pydantic>=3.0.1
Requires-Dist: requests>=2.23.0
Provides-Extra: doc
Requires-Dist: mdx-include>=1.4.1; extra == 'doc'
Requires-Dist: mkdocs-markdownextradata-plugin>=0.2.5; extra == 'doc'
Requires-Dist: mkdocs-material>=8.2.7; extra == 'doc'
Requires-Dist: mkdocs>=1.4.2; extra == 'doc'
Requires-Dist: mkdocstrings[python]>=0.19.1; extra == 'doc'
Provides-Extra: opentelemetry
Requires-Dist: opentelemetry-exporter-jaeger; extra == 'opentelemetry'
Requires-Dist: opentelemetry-exporter-otlp-proto-http; extra == 'opentelemetry'
Requires-Dist: opentelemetry-instrumentation-fastapi; extra == 'opentelemetry'
Requires-Dist: opentelemetry-instrumentation-httpx; extra == 'opentelemetry'
Requires-Dist: opentelemetry-instrumentation-requests; extra == 'opentelemetry'
Requires-Dist: opentelemetry-sdk; extra == 'opentelemetry'
Provides-Extra: test
Requires-Dist: httpx; extra == 'test'
Requires-Dist: mypy>=0.991; extra == 'test'
Requires-Dist: pandas; extra == 'test'
Requires-Dist: pre-commit; extra == 'test'
Requires-Dist: pytest-cov>=3.0.0; extra == 'test'
Requires-Dist: pytest>=7.1.3; extra == 'test'
Requires-Dist: reasoner-validator; extra == 'test'
Requires-Dist: scikit-learn; extra == 'test'
Requires-Dist: types-requests; extra == 'test'
Provides-Extra: web
Requires-Dist: gunicorn>=20.0.4; extra == 'web'
Requires-Dist: uvicorn>=0.15.0; extra == 'web'
